rimetool/__init__.py
rimetool/main.py
rimetool/rimetool_core/__init__.py
rimetool/rimetool_core/main.py
rimetool/rimetool_core/utils/Pinyin_Processor.py
rimetool/rimetool_core/utils/__init__.py
rimetool/rimetool_core/utils/common.py
rimetool/rimetool_core/utils/roman_to_chinese.py
rimetool/rimetool_core/utils/simple_chinese.py
rimetool/rimetool_core/utils/simple_english.py
rimetool/rimetool_core/utils/tosougou.py
rimetool/rimetool_core/utils/vcf.py
rimetool/rimetool_gui/gui_config.py
rimetool/rimetool_gui/new_app.py
rimetool/rimetool_gui/templates/development.html
rimetool/rimetool_gui/templates/new_index.html
rimetool/rimetool_gui/templates/style.css
rimetool-2.4.3.dist-info/licenses/LICENSE
rimetool-2.4.3.dist-info/METADATA
rimetool-2.4.3.dist-info/WHEEL
rimetool-2.4.3.dist-info/entry_points.txt
rimetool-2.4.3.dist-info/top_level.txt
rimetool-2.4.3.dist-info/RECORD
