Metadata-Version: 2.4
Name: rimetool
Version: 2.4.3
Summary: Rime输入法相关工具集，支持词库转换、通讯录导入等功能
License: Rimetool 专有软件许可协议 (Proprietary Software License)
Classifier: License :: Other/Proprietary License
Classifier: Programming Language :: Python :: 3
Classifier: Programming Language :: Python :: 3 :: Only
Requires-Python: >=3.10
License-File: LICENSE
Requires-Dist: argparse>=1.4.0
Requires-Dist: chardet>=5.2.0
Requires-Dist: click>=8.2.1
Requires-Dist: flask>=3.1.2
Requires-Dist: flask-cors>=6.0.1
Requires-Dist: jieba>=0.42.1
Requires-Dist: pypinyin>=0.55.0
Requires-Dist: zipp>=3.23.0
Dynamic: license-file
